oxford_colors/__init__.py
oxford_colors/oxford_colors.py
oxford_colors/examples/gallery.py
oxford_colors-1.0.0.dist-info/licenses/LICENSE
oxford_colors-1.0.0.dist-info/METADATA
oxford_colors-1.0.0.dist-info/WHEEL
oxford_colors-1.0.0.dist-info/top_level.txt
oxford_colors-1.0.0.dist-info/RECORD
