Metadata-Version: 2.4
Name: oxford_colors
Version: 1.0.0
Summary: Oxford University color palette for matplotlib
Author: Hakam Atassi
Author-email: Hakam Atassi <hakam.atassi@example.com>
Maintainer-email: Hakam Atassi <hakam.atassi@example.com>
License-Expression: MIT
Project-URL: Homepage, https://github.com/HakamAtassi/oxford_colors
Project-URL: Documentation, https://github.com/HakamAtassi/oxford_colors#readme
Project-URL: Repository, https://github.com/HakamAtassi/oxford_colors.git
Project-URL: Bug Tracker, https://github.com/HakamAtassi/oxford_colors/issues
Keywords: matplotlib,colors,oxford,university,palette,plotting
Classifier: Development Status :: 5 - Production/Stable
Classifier: Intended Audience :: Developers
Classifier: Intended Audience :: Science/Research
Classifier: Operating System :: OS Independent
Classifier: Programming Language :: Python :: 3
Classifier: Programming Language :: Python :: 3.8
Classifier: Programming Language :: Python :: 3.9
Classifier: Programming Language :: Python :: 3.10
Classifier: Programming Language :: Python :: 3.11
Classifier: Programming Language :: Python :: 3.12
Classifier: Programming Language :: Python :: 3.13
Classifier: Topic :: Scientific/Engineering :: Visualization
Classifier: Topic :: Software Development :: Libraries :: Python Modules
Requires-Python: >=3.8
License-File: LICENSE
Requires-Dist: matplotlib>=3.0.0
Requires-Dist: numpy>=1.18.0
Provides-Extra: dev
Requires-Dist: pytest>=6.0; extra == "dev"
Requires-Dist: pytest-cov>=2.0; extra == "dev"
Requires-Dist: black>=21.0; extra == "dev"
Requires-Dist: flake8>=3.8; extra == "dev"
Requires-Dist: mypy>=0.800; extra == "dev"
Provides-Extra: examples
Requires-Dist: jupyter>=1.0; extra == "examples"
Requires-Dist: notebook>=6.0; extra == "examples"
Dynamic: license-file
